LICENSE
MANIFEST.in
README.md
album-rsync.ini
setup.cfg
setup.py
album_rsync/__init__.py
album_rsync/__main__.py
album_rsync/_version.py
album_rsync/config.py
album_rsync/csv_walker.py
album_rsync/fake_storage.py
album_rsync/file.py
album_rsync/flickr_storage.py
album_rsync/folder.py
album_rsync/google_api.py
album_rsync/google_storage.py
album_rsync/local_storage.py
album_rsync/resiliently.py
album_rsync/storage.py
album_rsync/sync.py
album_rsync/throttle.py
album_rsync/tree_walker.py
album_rsync/utils.py
album_rsync/walker.py
album_rsync.egg-info/PKG-INFO
album_rsync.egg-info/SOURCES.txt
album_rsync.egg-info/dependency_links.txt
album_rsync.egg-info/entry_points.txt
album_rsync.egg-info/requires.txt
album_rsync.egg-info/top_level.txt
album_rsync.egg-info/zip-safe