Metadata-Version: 2.1
Name: album-rsync
Version: 2.0.5
Summary: A python script to manage synchronising a local directory of photos with a remote service based on an rsync interaction pattern
Home-page: http://www.phdesign.com.au/album-rsync
Author: Paul Heasley
Author-email: paul@phdesign.com.au
License: MIT
Download-URL: https://github.com/phdesign/album-rsync/archive/v2.0.5.tar.gz
Keywords: flickr,sync,rsync,photo,media,google,photos
Platform: UNKNOWN
